libname/__init__.py
libname/candle_patterns.py
libname/main.py
libname/trend_functions.py
libname/zerodha/__init__.py
libname/zerodha/kite_functions.py
libname/zerodha/kite_trade.py
algo_trading_helper_functions-0.0.2.dist-info/METADATA
algo_trading_helper_functions-0.0.2.dist-info/WHEEL
algo_trading_helper_functions-0.0.2.dist-info/top_level.txt
algo_trading_helper_functions-0.0.2.dist-info/RECORD
